whipcode/__init__.py
whipcode/exceptions.py
whipcode/languages.py
whipcode/whipcode.py
whipcode-0.2.1.dist-info/LICENSE
whipcode-0.2.1.dist-info/METADATA
whipcode-0.2.1.dist-info/WHEEL
whipcode-0.2.1.dist-info/RECORD
