Metadata-Version: 2.1
Name: whipcode
Version: 0.2.1
Summary: Official Python client for Whipcode API
Home-page: https://github.com/Whipcode-API/whipcode-py
License: MIT
Author: AnnikaV9
Author-email: carrot.moncher@gmail.com
Requires-Python: >=3.10,<4.0
Classifier: License :: OSI Approved :: MIT License
Classifier: Programming Language :: Python :: 3
Classifier: Programming Language :: Python :: 3.10
Classifier: Programming Language :: Python :: 3.11
Classifier: Programming Language :: Python :: 3.12
Classifier: Programming Language :: Python :: 3.13
Classifier: Topic :: Security
Classifier: Topic :: Software Development :: Libraries :: Python Modules
Requires-Dist: aiohttp (>=3.10.0,<3.11.0)
Requires-Dist: requests (>=2.32.0,<2.33.0)
Project-URL: Documentation, https://github.com/Whipcode-API/whipcode-py
Project-URL: Repository, https://github.com/Whipcode-API/whipcode-py
